trinity4bci/__init__.py
trinity4bci/_boardInfo.py
trinity4bci/client.py
trinity4bci/linux_run.py
trinity4bci/master.py
trinity4bci/out.py
trinity4bci/sfpr.py
trinity4bci/win_run.py
trinity4bci-0.0.5.dist-info/LICENSE
trinity4bci-0.0.5.dist-info/METADATA
trinity4bci-0.0.5.dist-info/WHEEL
trinity4bci-0.0.5.dist-info/top_level.txt
trinity4bci-0.0.5.dist-info/RECORD
