Metadata-Version: 2.1
Name: trinity4bci
Version: 0.0.5
Summary: A package for quickly developing and prototyping Neurotechnology projects
Home-page: UNKNOWN
Author: Leonardo Ferrisi
Author-email: ferrisil@union.edu
License: Creative Commons Public License
Keywords: neurotechnology
Platform: UNKNOWN
Classifier: Development Status :: 4 - Beta
Classifier: Intended Audience :: Developers
Classifier: Intended Audience :: Science/Research
Classifier: Operating System :: Microsoft :: Windows :: Windows 10
Classifier: Operating System :: Unix
Classifier: License :: OSI Approved
Classifier: Programming Language :: Python :: 3
Classifier: Topic :: Adaptive Technologies
Classifier: Topic :: Scientific/Engineering
Requires-Dist: brainflow
Requires-Dist: numpy
Requires-Dist: zmq
